LICENSE
README.md
setup.py
PySpective.egg-info/PKG-INFO
PySpective.egg-info/SOURCES.txt
PySpective.egg-info/dependency_links.txt
PySpective.egg-info/top_level.txt
pyspective/__init__.py
pyspective/pyspective.py