Metadata-Version: 2.1
Name: PySpective
Version: 0.0.2
Summary: A Google's Perspective API wrapper
Home-page: https://github.com/Brain-Flooder/PySpective/
Author: Brain-Flooder
Author-email: brainflooder9985@gmail.com
License: UNKNOWN
Platform: UNKNOWN
Classifier: Programming Language :: Python :: 3
Classifier: License :: OSI Approved :: MIT License
Classifier: Operating System :: OS Independent
Requires-Python: >=3.8
